howdididolib/__init__.py
howdididolib/authentication.py
howdididolib/bookings.py
howdididolib/console.py
howdididolib/const.py
howdididolib/exceptions.py
howdididolib/fixtures.py
howdididolib/types.py
howdididolib-0.4.0.dist-info/METADATA
howdididolib-0.4.0.dist-info/WHEEL
howdididolib-0.4.0.dist-info/entry_points.txt
howdididolib-0.4.0.dist-info/licenses/LICENSE
howdididolib-0.4.0.dist-info/RECORD
