Metadata-Version: 2.4
Name: howdididolib
Version: 0.4.0
Summary: How Did I Do library
Author-email: Jonathon Adler <pypi@jadler.fea.st>
License: MIT
License-File: LICENSE
Classifier: License :: OSI Approved :: MIT License
Classifier: Operating System :: OS Independent
Classifier: Programming Language :: Python :: 3
Requires-Python: >=3.10
Requires-Dist: aiohttp>=3.9.0
Requires-Dist: beautifulsoup4>=4.13.3
Requires-Dist: certifi>=2025.0.0
Requires-Dist: click>=8.1.8
Requires-Dist: rich>=10.16.2
Requires-Dist: typer>=0.12.5
Provides-Extra: dev
Requires-Dist: aioresponses>=0.7.0; extra == 'dev'
Requires-Dist: pytest-asyncio>=0.24.0; extra == 'dev'
Requires-Dist: pytest-cov>=5.0.0; extra == 'dev'
Requires-Dist: pytest>=8.3.0; extra == 'dev'
